mltrain/__init__.py
mltrain/main.py
mltrain/supervised/DecisionTree.py
mltrain/supervised/KNN.py
mltrain/supervised/KernelSVM.py
mltrain/supervised/LinearRegression.py
mltrain/supervised/LogisticRegression.py
mltrain/supervised/NaiveBayes.py
mltrain/supervised/RandomForest.py
mltrain/supervised/__init__.py
mltrain/unsupervised/DBSCAN.py
mltrain/unsupervised/KMeans.py
mltrain/unsupervised/PCA.py
mltrain/unsupervised/__init__.py
mltrain-0.4.1.dist-info/LICENSE
mltrain-0.4.1.dist-info/METADATA
mltrain-0.4.1.dist-info/WHEEL
mltrain-0.4.1.dist-info/top_level.txt
mltrain-0.4.1.dist-info/RECORD
