Metadata-Version: 2.1
Name: mltrain
Version: 0.4.1
Home-page: https://github.com/Abfa41/mltrain_python.git
Author: Abdul Faatih Siddiqui
License-File: LICENSE
Requires-Dist: numpy
Requires-Dist: tensorflow
